[
  {
    "Mountain": {
      "title": "Mountain",
      "images": [
        "/Mountain2.jpg",
        "/Mountain1.jpg",
        "/Mountain2.jpg",
        "/Mountain3.jpg",
        "/Mountain1.jpg",
        "/Mountain2.jpg",
        "/Mountain3.jpg",
        "/Mountain1.jpg"
      ]
    },
    "Beaches": {
      "title": "Beach",
      "images": [
        "/Beaches2.jpg",
        "/Beaches1.jpg",
        "/Beaches2.jpg",
        "/Beaches3.jpg",
        "/Beaches1.jpg",
        "/Beaches2.jpg",
        "/Beaches3.jpg",
        "/Beaches1.jpg"
      ]
    },
    "Birds": {
      "title": "Bird",
      "images": [
        "/Birds2.jpg",
        "/Birds1.jpg",
        "/Birds4.jpg",
        "/Birds3.jpg",
        "/Birds1.jpg",
        "/Birds2.jpg",
        "/Birds3.jpg",
        "/Birds4.jpg"
      ]
    },
    "Food": {
      "title": "Food",
      "images": [
        "/Food2.jpg",
        "/Food1.jpg",
        "/Food2.jpg",
        "/Food3.jpg",
        "/Food1.jpg",
        "/Food2.jpg",
        "/Food3.jpg",
        "/Food1.jpg"
      ]
    }
  }
]
